woke/__init__.py
woke/analysis/__init__.py
woke/analysis/cfg.py
woke/analysis/detectors/__init__.py
woke/analysis/detectors/api.py
woke/analysis/detectors/axelar/__init__.py
woke/analysis/detectors/axelar/proxy_contract_id.py
woke/analysis/detectors/balance_state_var.py
woke/analysis/detectors/bug_empty_byte_array_copy.py
woke/analysis/detectors/call_options_not_called.py
woke/analysis/detectors/missing_return.py
woke/analysis/detectors/msg_value_nonpayable_function.py
woke/analysis/detectors/overflow_calldata_tuple_reencoding_bug.py
woke/analysis/detectors/ownable.py
woke/analysis/detectors/proxy_contract_selector_clashes.py
woke/analysis/detectors/reentrancy.py
woke/analysis/detectors/unchecked_return_value.py
woke/analysis/detectors/unsafe_delegatecall.py
woke/analysis/detectors/unsafe_selfdestruct.py
woke/analysis/detectors/unsafe_tx_origin.py
woke/analysis/detectors/unused_contract.py
woke/analysis/detectors/utils.py
woke/ast/__init__.py
woke/ast/enums.py
woke/ast/ir/__init__.py
woke/ast/ir/abc.py
woke/ast/ir/declaration/__init__.py
woke/ast/ir/declaration/abc.py
woke/ast/ir/declaration/contract_definition.py
woke/ast/ir/declaration/enum_definition.py
woke/ast/ir/declaration/enum_value.py
woke/ast/ir/declaration/error_definition.py
woke/ast/ir/declaration/event_definition.py
woke/ast/ir/declaration/function_definition.py
woke/ast/ir/declaration/modifier_definition.py
woke/ast/ir/declaration/struct_definition.py
woke/ast/ir/declaration/user_defined_value_type_definition.py
woke/ast/ir/declaration/variable_declaration.py
woke/ast/ir/expression/__init__.py
woke/ast/ir/expression/abc.py
woke/ast/ir/expression/assignment.py
woke/ast/ir/expression/binary_operation.py
woke/ast/ir/expression/conditional.py
woke/ast/ir/expression/elementary_type_name_expression.py
woke/ast/ir/expression/function_call.py
woke/ast/ir/expression/function_call_options.py
woke/ast/ir/expression/identifier.py
woke/ast/ir/expression/index_access.py
woke/ast/ir/expression/index_range_access.py
woke-3.6.2.dist-info/LICENSE
woke-3.6.2.dist-info/METADATA
woke-3.6.2.dist-info/WHEEL
woke-3.6.2.dist-info/entry_points.txt
woke-3.6.2.dist-info/RECORD
