Metadata-Version: 2.1
Name: woke
Version: 3.6.2
Summary: Woke is a Python-based development and testing framework for Solidity.
Home-page: https://ackeeblockchain.com
License: ISC
Keywords: ethereum,solidity,security,testing,development,framework,audit
Author: Ackee Blockchain
Requires-Python: >=3.7.9,<4.0.0
Classifier: License :: OSI Approved
Classifier: Programming Language :: Python :: 3
Classifier: Programming Language :: Python :: 3.8
Classifier: Programming Language :: Python :: 3.9
Classifier: Programming Language :: Python :: 3.10
Classifier: Programming Language :: Python :: 3.11
Classifier: Programming Language :: Python :: 3.12
Provides-Extra: dev
Provides-Extra: tests
Requires-Dist: GitPython (>=3.1.20,<4.0.0) ; extra == "tests"
Requires-Dist: abch_tree_sitter (>=1.1.1,<2.0.0)
Requires-Dist: abch_tree_sitter_solidity (>=1.2.0,<2.0.0)
Requires-Dist: aiofiles (>=0.8,<0.9)
Requires-Dist: aiohttp (>=3.8,<4.0)
Requires-Dist: black (>=22,<23) ; extra == "dev"
Requires-Dist: cairosvg (>=2.7,<3.0) ; extra == "dev"
Requires-Dist: click (>=8,<9)
Requires-Dist: eth-abi (>=4.0.0b2,<5.0.0)
Requires-Dist: eth-account (>=0.8,<0.9)
Requires-Dist: eth-hash[pycryptodome] (>=0.5.1,<0.6.0)
Requires-Dist: eth-utils (>=2.1,<3.0)
Requires-Dist: graphviz (>=0.19,<0.20)
Requires-Dist: intervaltree (>=3.1,<4.0)
Requires-Dist: ipdb (>=0.13.9,<0.14.0)
Requires-Dist: isort (>=5,<6) ; extra == "dev"
Requires-Dist: lazy-import (>=0.2.2,<0.3.0)
Requires-Dist: mike @ git+https://github.com/jimporter/mike.git ; extra == "dev"
Requires-Dist: mkdocs-material (>=9,<10) ; extra == "dev"
Requires-Dist: mkdocstrings (>=0.20,<0.21) ; extra == "dev"
Requires-Dist: mkdocstrings-python (>=1,<2) ; extra == "dev"
Requires-Dist: networkx (>=2.5,<3.0)
Requires-Dist: parsimonious (>=0.9,<0.10)
Requires-Dist: pathvalidate (>=2.5,<3.0)
Requires-Dist: pillow (>=9,<10) ; extra == "dev"
Requires-Dist: pydantic (>=1.9.1,<2.0.0)
Requires-Dist: pygments (>=2,<3) ; extra == "dev"
Requires-Dist: pymdown-extensions (>=9,<10) ; extra == "dev"
Requires-Dist: pytest (>=7,<8)
Requires-Dist: pytest-asyncio (>=0.17,<0.18) ; extra == "tests"
Requires-Dist: pywin32 (>=302) ; sys_platform == "win32"
Requires-Dist: rich (>=13.3.2,<14.0.0)
Requires-Dist: rich-click (>=1.6,<2.0)
Requires-Dist: tblib (>=1.7,<2.0)
Requires-Dist: tomli (>=2,<3)
Requires-Dist: typing-extensions (>=4,<5)
Requires-Dist: watchdog (>=2.2.0,<2.3.0)
Requires-Dist: websocket-client (>=1.4,<2.0)
Project-URL: Announcement, https://ackeeblockchain.com/blog/woke-our-development-and-testing-framework-for-solidity/
Project-URL: Documentation, https://ackeeblockchain.com/woke/docs/latest
Project-URL: Repository, https://github.com/Ackee-Blockchain/woke
Project-URL: VS Code Extension, https://marketplace.visualstudio.com/items?itemName=AckeeBlockchain.tools-for-solidity
